tk_animations.py
tk_animations-0.1.0.dist-info/licenses/LICENSE
tk_animations-0.1.0.dist-info/METADATA
tk_animations-0.1.0.dist-info/WHEEL
tk_animations-0.1.0.dist-info/top_level.txt
tk_animations-0.1.0.dist-info/RECORD
