Metadata-Version: 2.4
Name: tk-animations
Version: 0.1.0
Summary: A Tkinter animation library with 10 reusable animations.
Home-page: https://github.com/itsDevlune/TkAnimator
Author: itsDevLune
Author-email: officaldevanarayan@gmail.com
License: MIT
Classifier: Development Status :: 3 - Alpha
Requires-Python: >=3.6
License-File: LICENSE
Dynamic: author
Dynamic: author-email
Dynamic: classifier
Dynamic: description
Dynamic: description-content-type
Dynamic: home-page
Dynamic: license
Dynamic: license-file
Dynamic: requires-python
Dynamic: summary
